{
  "9:00": [{
    "duration": "15 mins",
    "session": "101",
    "full": true
  }],
  "9:15": [{
    "duration": "50 mins",
    "session": "102",
    "full": true
  }],
  "10:10": [{
    "duration": "50 mins",
    "session": "103",
    "full": true
  }],
  "11:00": [{
    "duration": "30 mins",
    "session": "104",
    "full": true
  }],
  "11:30": [{
    "duration": "30 mins",
    "session": "105",
    "full": true
  }],
  "12:00": [{
    "duration": "60 mins",
    "session": "106",
    "full": true
  }],
  "13:00": [{
    "duration": "60 mins",
    "session": "107",
    "span": 4
  }, {
    "duration": "60 mins",
    "session": "111",
    "span": 4
  }, {
    "duration": "75 mins",
    "session": "115",
    "span": 5
  }, {
    "duration": "2 hours",
    "session": "119",
    "span": 9
  }],
  "14:00": [{
    "duration": "60 mins",
    "session": "108",
    "span": 4
  }, {
    "duration": "60 mins",
    "session": "112",
    "span": 4
  }],
  "14:15": [{
    "duration": "60 mins",
    "session": "116",
    "span": 4
  }],
  "15:00": [{
    "duration": "75 mins",
    "session": "109",
    "span": 5
  }, {
    "duration": "75 mins",
    "session": "113",
    "span": 5
  }],
  "15:15": [{
    "duration": "90 mins",
    "session": "117",
    "span": 6
  }, {
    "duration": "90 mins",
    "session": "120",
    "span": "9"
  }],
  "16:15": [{
    "duration": "75 mins",
    "session": "110",
    "span": 5
  }, {
    "duration": "75 mins",
    "session": "114",
    "span": 5
  }],
  "16:45": [{
    "duration": "45 mins",
    "session": "118",
    "span": 3
  }],
  "17:30": [{
    "duration": "15 mins",
    "session": "122",
    "full": true
  }]
}
